minibench.egg-info/PKG-INFO
minibench.egg-info/dependency_links.txt
minibench.egg-info/top_level.txt
minibench.egg-info/not-zip-safe
minibench.egg-info/entry_points.txt
minibench.egg-info/requires.txt
minibench.egg-info/SOURCES.txt
minibench-0.1.0.dist-info/METADATA
minibench-0.1.0.dist-info/WHEEL
minibench-0.1.0.dist-info/top_level.txt
minibench-0.1.0.dist-info/RECORD
minibench-0.1.0.dist-info/entry_points.txt
minibench-0.1.0.dist-info/DESCRIPTION.rst
minibench-0.1.0.dist-info/metadata.json
tests/test_reporter.py
tests/test_runner.py
tests/test_benchmark.py
tests/test_utils.py
tests/__init__.py
tests/test_cli.py
minibench/runner.py
minibench/cli.py
minibench/benchmark.py
minibench/__init__.py
minibench/utils.py
minibench/_compat.py
minibench/__about__.py
minibench/report.py
minibench/__pycache__/report.cpython-35.pyc
minibench/__pycache__/runner.cpython-35.pyc
minibench/__pycache__/utils.cpython-35.pyc
minibench/__pycache__/cli.cpython-35.pyc
minibench/__pycache__/__about__.cpython-35.pyc
minibench/__pycache__/__init__.cpython-35.pyc
minibench/__pycache__/_compat.cpython-35.pyc
minibench/__pycache__/benchmark.cpython-35.pyc
