Metadata-Version: 2.0
Name: minibench
Version: 0.1.0
Summary: A really simple benchmark tool
Home-page: https://github.com/noirbizarre/minibench
Author: Axel Haustant
Author-email: noirbizarre+minibench@gmail.com
License: MIT
Keywords: benchmark test development reporting performance
Platform: UNKNOWN
Classifier: Development Status :: 3 - Alpha
Classifier: Programming Language :: Python
Classifier: Environment :: Web Environment
Classifier: Operating System :: OS Independent
Classifier: Intended Audience :: Developers
Classifier: Topic :: System :: Software Distribution
Classifier: Programming Language :: Python
Classifier: Programming Language :: Python :: 2
Classifier: Programming Language :: Python :: 2.7
Classifier: Programming Language :: Python :: 3
Classifier: Programming Language :: Python :: 3.3
Classifier: Programming Language :: Python :: 3.4
Classifier: Programming Language :: Python :: 3.5
Classifier: Programming Language :: Python :: Implementation :: PyPy
Classifier: Topic :: Software Development :: Libraries :: Python Modules
Classifier: License :: OSI Approved :: MIT License
Requires-Dist: click
Requires-Dist: six
Provides-Extra: test
Requires-Dist: nose; extra == 'test'
Requires-Dist: rednose; extra == 'test'
Requires-Dist: markdown; extra == 'test'
Requires-Dist: docutils; extra == 'test'
